polors/__init__.py
polors/_utils.py
polors/gurobi.py
polors-0.2.4.dist-info/METADATA
polors-0.2.4.dist-info/WHEEL
polors-0.2.4.dist-info/licenses/LICENSE
polors-0.2.4.dist-info/RECORD
