Metadata-Version: 2.3
Name: polors
Version: 0.2.4
Summary: Add your description here
License-File: LICENSE
Requires-Python: >=3.11
Requires-Dist: polars>=1.9
Provides-Extra: gurobi
Requires-Dist: gurobipy>=11.0.3; extra == 'gurobi'
Requires-Dist: numpy>=2.1.2; extra == 'gurobi'
